SC_search/__init__.py
SC_search/directi.py
SC_search-0.0.1.dist-info/LICENSE
SC_search-0.0.1.dist-info/METADATA
SC_search-0.0.1.dist-info/WHEEL
SC_search-0.0.1.dist-info/top_level.txt
SC_search-0.0.1.dist-info/RECORD
