Metadata-Version: 2.1
Name: SC-search
Version: 0.0.1
Summary: Single-cell search tool
Home-page: https://github.com/KongNingZhe/SC-search
Author: Cheng Zhang
Author-email: Richard_Z@88.com
License: UNKNOWN
Platform: UNKNOWN
Classifier: Programming Language :: Python :: 3.6
Classifier: License :: OSI Approved :: MIT License
Classifier: Operating System :: OS Independent
Requires-Dist: numpy
Requires-Dist: numba (>=0.39.0)
Requires-Dist: scipy (>=1.0.0)
Requires-Dist: joblib (>=0.12.0)
Requires-Dist: scikit-learn (>=0.17.0)
Requires-Dist: tqdm (>=4.12.0)
Requires-Dist: pandas (>=0.21.0)
Requires-Dist: h5py (>=2.7.0)
Requires-Dist: python-igraph (>=0.7.1)
Requires-Dist: pronto (>=0.10.2)
Requires-Dist: seaborn (>=0.9.0)
Requires-Dist: umap-learn (>=0.2.1)
Requires-Dist: anndata (>=0.6.14)
Requires-Dist: loompy (>=2.0.6)
Requires-Dist: statsmodels (>=0.8.0)
Requires-Dist: plotly
